shifthtml/__init__.py
shifthtml/compat.py
shifthtml/node.py
shifthtml/py.typed
shifthtml/render.py
shifthtml/tags.py
shifthtml-0.1.0.dist-info/METADATA
shifthtml-0.1.0.dist-info/WHEEL
shifthtml-0.1.0.dist-info/licenses/LICENSE
shifthtml-0.1.0.dist-info/RECORD
