Metadata-Version: 2.4
Name: shifthtml
Version: 0.1.0
Summary: Add your description here
License-File: LICENSE
Requires-Python: >=3.13
